boostspace_mcp/__init__.py
boostspace_mcp/api_client.py
boostspace_mcp/config.py
boostspace_mcp/server.py
boostspace_mcp/spec_cache.py
boostspace_mcp/spec_loader.py
boostspace_mcp/tool_registry.py
boostspace_mcp/version.py
iflow_mcp_boostspace_boostspace_mcp_server-0.1.1.dist-info/licenses/LICENSE
iflow_mcp_boostspace_boostspace_mcp_server-0.1.1.dist-info/METADATA
iflow_mcp_boostspace_boostspace_mcp_server-0.1.1.dist-info/WHEEL
iflow_mcp_boostspace_boostspace_mcp_server-0.1.1.dist-info/entry_points.txt
iflow_mcp_boostspace_boostspace_mcp_server-0.1.1.dist-info/top_level.txt
iflow_mcp_boostspace_boostspace_mcp_server-0.1.1.dist-info/RECORD
