Metadata-Version: 2.4
Name: iflow-mcp_boostspace_boostspace-mcp-server
Version: 0.1.1
Summary: A Model Context Protocol (MCP) server for Boost.space
Maintainer-email: "Boost.space" <team@boost.space>
License: MIT License
Project-URL: Homepage, https://github.com/boostspace/boostspace-mcp-server
Project-URL: Bug Tracker, https://github.com/boostspace/boostspace-mcp-server/issues
Requires-Python: >=3.11
License-File: LICENSE
Requires-Dist: mcp[cli]>=1.6.0
Requires-Dist: requests>=2.28.0
Provides-Extra: dev
Requires-Dist: pytest; extra == "dev"
Requires-Dist: ruff; extra == "dev"
Requires-Dist: setuptools; extra == "dev"
Requires-Dist: liccheck; extra == "dev"
Provides-Extra: tests
Requires-Dist: pytest; extra == "tests"
Dynamic: license-file
